{"meta":{"level":"county","generated":"2026-07-20","zillow_latest_month":"2026-06","acs_year":2024,"mortgage_rate":0.0655,"n":21,"history_start":"2024-07","history_months":24,"domains":{"zhvi":[303161.639,593030.8648,788033.4384],"appreciation_1yr":[0.0066,0.0316,0.0571],"appreciation_5yr":[0.0543,0.0672,0.0832],"zori":[1948.3799,2303.5285,2949.4789],"rent_yield":[0.0396,0.0568,0.0694],"days_to_pending":[13.6667,17.0,30.3333],"price_cut_share":[0.1197,0.1618,0.2105],"sale_to_list":[0.9779,1.0074,1.0443],"inventory_yoy":[-0.0417,0.0871,0.1736],"income":[78050.0,100869.0,140374.0],"value_to_income":[3.7914,4.9636,8.3453],"buy_to_rent":[0.8796,1.0741,1.5456],"zhvi__m1":[-0.0056,0,0.0056],"zhvi__m3":[-0.0163,0,0.0163],"zhvi__m12":[-0.0571,0,0.0571],"zori__m1":[-0.0082,0,0.0082],"zori__m3":[-0.0153,0,0.0153],"zori__m12":[-0.046,0,0.046],"days_to_pending__m1":[-5.3333,0,5.3333],"days_to_pending__m3":[-16.3333,0,16.3333],"days_to_pending__m12":[-2.6667,0,2.6667],"price_cut_share__m1":[-0.0192,0,0.0192],"price_cut_share__m3":[-0.0408,0,0.0408],"price_cut_share__m12":[-0.0235,0,0.0235],"inventory__m1":[-0.1905,0,0.1905],"inventory__m3":[-0.4387,0,0.4387],"inventory__m12":[-0.1736,0,0.1736],"signal_distressed_vacancy":[0.0089,0.0173,0.0292],"signal_absentee":[0.1627,0.2902,0.551],"signal_free_clear":[0.317,0.3551,0.4132],"signal_long_tenure":[0.4763,0.5395,0.5632],"signal_seasonal":[0.0016,0.0045,0.1345],"signal_older_stock":[0.3474,0.469,0.6923],"signal_senior_owners":[0.2871,0.3163,0.4327],"signal_cost_burdened":[0.245,0.2721,0.3431],"signal_small_multifamily":[0.0532,0.0794,0.3074]},"signal_coverage":{"distressed_vacancy":21,"absentee":21,"free_clear":21,"long_tenure":21,"seasonal":21,"older_stock":21,"senior_owners":21,"cost_burdened":21,"small_multifamily":21},"scored":{"overall":21,"investment":21,"hotness":21,"affordability":21}},"geos":{"34003":{"name":"Bergen","scores":{"overall":36.4,"investment":41.9,"hotness":54.2,"affordability":15.6},"rank":{"investment":12,"hotness":9,"affordability":19,"overall":17},"coverage":{"investment":1.0,"hotness":1.0,"affordability":1.0},"stats":{"zhvi":788033,"appreciation_1yr":0.0571,"appreciation_5yr":0.0587,"zori":2909,"rent_yield":0.0443,"days_to_pending":18.3,"sale_to_list":1.0238,"price_cut_share":0.1219,"inventory_yoy":0.1365,"income":124884,"value_to_income":6.31,"buy_to_rent":1.38},"trends":{"zhvi":{"m1":0.0041,"m3":0.015,"m12":0.0571},"zori":{"m1":0.002,"m3":0.0053,"m12":0.034},"days_to_pending":{"m1":-2.6667,"m3":-11.0,"m12":1.0},"price_cut_share":{"m1":0.0119,"m3":0.0227,"m12":0.0129},"inventory":{"m1":0.141,"m3":0.3543,"m12":0.1365}},"history":{"zhvi":[716251,720382,725282,729386,732600,734133,735004,736751,739483,742994,745695,747716,749534,750323,752454,756344,761492,766922,771340,776388,781513,784954,788031,791116],"zori":[2752,2760,2765,2771,2767,2779,2782,2791,2799,2805,2817,2820,2830,2841,2848,2857,2870,2877,2887,2896,2899,2905,2907,2916]},"signals":{"distressed_vacancy":0.0157,"absentee":0.3466,"free_clear":0.3839,"long_tenure":0.5632,"seasonal":0.0022,"older_stock":0.644,"senior_owners":0.3296,"cost_burdened":0.3041,"small_multifamily":0.1823},"signal_pct":{"distressed_vacancy":33.3,"absentee":66.7,"free_clear":76.2,"long_tenure":95.2,"seasonal":28.6,"older_stock":85.7,"senior_owners":81.0,"cost_burdened":81.0,"small_multifamily":81.0},"signal_n":{"distressed_vacancy":5790,"absentee":123102,"free_clear":89083,"long_tenure":130677,"seasonal":801,"older_stock":238023,"senior_owners":76468,"cost_burdened":70555,"small_multifamily":67382}},"34023":{"name":"Middlesex","scores":{"overall":37.2,"investment":39.0,"hotness":32.1,"affordability":39.7},"rank":{"investment":15,"hotness":17,"affordability":14,"overall":16},"coverage":{"investment":1.0,"hotness":1.0,"affordability":1.0},"stats":{"zhvi":593031,"appreciation_1yr":0.03,"appreciation_5yr":0.0672,"zori":2564,"rent_yield":0.0519,"days_to_pending":21.7,"sale_to_list":1.0074,"price_cut_share":0.1506,"inventory_yoy":0.2033,"income":111549,"value_to_income":5.32,"buy_to_rent":1.18},"trends":{"zhvi":{"m1":-0.0005,"m3":0.0049,"m12":0.03},"zori":{"m1":0.0011,"m3":0.0033,"m12":0.0153},"days_to_pending":{"m1":-3.0,"m3":-13.0,"m12":2.6667},"price_cut_share":{"m1":0.009,"m3":0.0202,"m12":0.0184},"inventory":{"m1":0.1216,"m3":0.2996,"m12":0.2033}},"history":{"zhvi":[545132,549393,553820,557856,561782,564505,566644,568840,571535,574424,575995,576819,576856,576858,577323,579091,581569,584453,587066,590185,593156,593792,593071,592229],"zori":[2460,2464,2474,2472,2477,2485,2493,2505,2510,2518,2526,2531,2534,2542,2547,2556,2556,2555,2554,2554,2558,2562,2564,2566]},"signals":{"distressed_vacancy":0.0135,"absentee":0.3635,"free_clear":0.3694,"long_tenure":0.5507,"seasonal":0.0021,"older_stock":0.4573,"senior_owners":0.3123,"cost_burdened":0.2835,"small_multifamily":0.1173},"signal_pct":{"distressed_vacancy":23.8,"absentee":76.2,"free_clear":66.7,"long_tenure":71.4,"seasonal":23.8,"older_stock":47.6,"senior_owners":42.9,"cost_burdened":57.1,"small_multifamily":76.2},"signal_n":{"distressed_vacancy":4294,"absentee":111894,"free_clear":72370,"long_tenure":107879,"seasonal":663,"older_stock":145404,"senior_owners":61179,"cost_burdened":55525,"small_multifamily":37294}},"34013":{"name":"Essex","scores":{"overall":35.9,"investment":33.2,"hotness":75.4,"affordability":5.0},"rank":{"investment":19,"hotness":1,"affordability":20,"overall":18},"coverage":{"investment":1.0,"hotness":1.0,"affordability":1.0},"stats":{"zhvi":674209,"appreciation_1yr":0.0368,"appreciation_5yr":0.0592,"zori":2272,"rent_yield":0.0404,"days_to_pending":14.7,"sale_to_list":1.0825,"price_cut_share":0.117,"inventory_yoy":0.0996,"income":80789,"value_to_income":8.35,"buy_to_rent":1.51},"trends":{"zhvi":{"m1":0.0012,"m3":0.0056,"m12":0.0368},"zori":{"m1":0.0009,"m3":0.0031,"m12":0.0142},"days_to_pending":{"m1":-1.3333,"m3":-9.3333,"m12":0.3333},"price_cut_share":{"m1":0.0067,"m3":0.0173,"m12":-0.0019},"inventory":{"m1":0.1225,"m3":0.3623,"m12":0.0996}},"history":{"zhvi":[630605,634418,637756,640061,641745,643103,644755,646302,647320,648655,650065,652065,654179,655388,656896,659079,662440,665782,668384,670403,672606,673382,674181,675065],"zori":[2158,2163,2165,2164,2181,2192,2216,2217,2227,2232,2244,2244,2249,2255,2264,2274,2269,2268,2259,2268,2268,2272,2270,2274]},"signals":{"distressed_vacancy":0.0268,"absentee":0.551,"free_clear":0.317,"long_tenure":0.5292,"seasonal":0.0016,"older_stock":0.6511,"senior_owners":0.3006,"cost_burdened":0.3288,"small_multifamily":0.2795},"signal_pct":{"distressed_vacancy":85.7,"absentee":95.2,"free_clear":9.5,"long_tenure":28.6,"seasonal":14.3,"older_stock":90.5,"senior_owners":28.6,"cost_burdened":90.5,"small_multifamily":90.5},"signal_n":{"distressed_vacancy":9043,"absentee":176209,"free_clear":45508,"long_tenure":75977,"seasonal":549,"older_stock":219394,"senior_owners":43158,"cost_burdened":47214,"small_multifamily":94178}},"34017":{"name":"Hudson","scores":{"overall":32.7,"investment":34.8,"hotness":39.6,"affordability":24.7},"rank":{"investment":18,"hotness":14,"affordability":16,"overall":20},"coverage":{"investment":1.0,"hotness":1.0,"affordability":1.0},"stats":{"zhvi":647173,"appreciation_1yr":0.0066,"appreciation_5yr":0.0334,"zori":3062,"rent_yield":0.0568,"days_to_pending":30.3,"sale_to_list":0.997,"price_cut_share":0.1618,"inventory_yoy":0.019,"income":91795,"value_to_income":7.05,"buy_to_rent":1.07},"trends":{"zhvi":{"m1":0.0007,"m3":0.0072,"m12":0.0066},"zori":{"m1":0.0024,"m3":0.0044,"m12":0.0244},"days_to_pending":{"m1":-6.6667,"m3":-19.3333,"m12":-0.6667},"price_cut_share":{"m1":0.0115,"m3":0.0372,"m12":-0.0054},"inventory":{"m1":0.0899,"m3":0.2257,"m12":0.019}},"history":{"zhvi":[622493,626164,630993,635364,639047,641368,641734,641052,640643,641939,643004,643784,643650,643052,642530,641706,640655,639311,639734,642330,645631,647190,647265,647064],"zori":[2902,2907,2913,2930,2941,2949,2957,2969,2980,2988,2989,2991,3003,3013,3022,3026,3032,3041,3047,3050,3050,3053,3062,3072]},"signals":{"distressed_vacancy":0.0172,"absentee":0.6928,"free_clear":0.3439,"long_tenure":0.4759,"seasonal":0.0063,"older_stock":0.5337,"senior_owners":0.2728,"cost_burdened":0.3431,"small_multifamily":0.3186},"signal_pct":{"distressed_vacancy":47.6,"absentee":100.0,"free_clear":38.1,"long_tenure":4.8,"seasonal":61.9,"older_stock":71.4,"senior_owners":4.8,"cost_burdened":95.2,"small_multifamily":100.0},"signal_n":{"distressed_vacancy":5507,"absentee":207608,"free_clear":31666,"long_tenure":43817,"seasonal":2034,"older_stock":171286,"senior_owners":25121,"cost_burdened":31592,"small_multifamily":102271}},"34025":{"name":"Monmouth","scores":{"overall":49.0,"investment":60.6,"hotness":68.5,"affordability":20.6},"rank":{"investment":7,"hotness":4,"affordability":17,"overall":11},"coverage":{"investment":1.0,"hotness":1.0,"affordability":1.0},"stats":{"zhvi":782802,"appreciation_1yr":0.0396,"appreciation_5yr":0.0709,"zori":2937,"rent_yield":0.045,"days_to_pending":15.0,"sale_to_list":1.011,"price_cut_share":0.1474,"inventory_yoy":-0.0417,"income":124845,"value_to_income":6.27,"buy_to_rent":1.35},"trends":{"zhvi":{"m1":0.0056,"m3":0.0163,"m12":0.0396},"zori":{"m1":0.0035,"m3":0.0141,"m12":0.0418},"days_to_pending":{"m1":-1.6667,"m3":-10.0,"m12":0.0},"price_cut_share":{"m1":0.0127,"m3":0.0218,"m12":-0.0006},"inventory":{"m1":0.1261,"m3":0.3247,"m12":-0.0417}},"history":{"zhvi":[731268,734859,738603,741925,744251,745923,747162,749012,750706,752568,753322,753127,752400,751438,752187,755171,759162,763091,766375,769984,774361,778208,782768,787429],"zori":[2731,2749,2754,2773,2777,2796,2809,2815,2808,2803,2817,2837,2853,2860,2862,2865,2873,2882,2885,2893,2910,2931,2939,2941]},"signals":{"distressed_vacancy":0.0135,"absentee":0.2445,"free_clear":0.3596,"long_tenure":0.5253,"seasonal":0.0358,"older_stock":0.4414,"senior_owners":0.3274,"cost_burdened":0.2721,"small_multifamily":0.0651},"signal_pct":{"distressed_vacancy":28.6,"absentee":33.3,"free_clear":61.9,"long_tenure":23.8,"seasonal":81.0,"older_stock":38.1,"senior_owners":76.2,"cost_burdened":52.4,"small_multifamily":28.6},"signal_n":{"distressed_vacancy":3662,"absentee":61539,"free_clear":68383,"long_tenure":99904,"seasonal":9685,"older_stock":119359,"senior_owners":62262,"cost_burdened":51743,"small_multifamily":17597}},"34029":{"name":"Ocean","scores":{"overall":52.3,"investment":77.0,"hotness":34.0,"affordability":43.2},"rank":{"investment":3,"hotness":16,"affordability":12,"overall":9},"coverage":{"investment":1.0,"hotness":1.0,"affordability":1.0},"stats":{"zhvi":553095,"appreciation_1yr":0.0446,"appreciation_5yr":0.0808,"zori":2696,"rent_yield":0.0585,"days_to_pending":21.3,"sale_to_list":0.9877,"price_cut_share":0.2003,"inventory_yoy":0.0377,"income":89863,"value_to_income":6.15,"buy_to_rent":1.04},"trends":{"zhvi":{"m1":0.0032,"m3":0.0098,"m12":0.0446},"zori":{"m1":0.0047,"m3":0.0147,"m12":0.0339},"days_to_pending":{"m1":-3.0,"m3":-13.3333,"m12":1.3333},"price_cut_share":{"m1":0.0192,"m3":0.0408,"m12":0.0077},"inventory":{"m1":0.0966,"m3":0.2016,"m12":0.0377}},"history":{"zhvi":[514373,517272,520419,522958,524492,525615,526194,527111,527498,528436,529362,530695,532152,533730,535801,538513,541269,543969,545891,547701,549545,551360,553037,554887],"zori":[2498,2490,2525,2521,2565,2577,2597,2574,2591,2591,2611,2621,2626,2649,2642,2659,2642,2643,2637,2664,2670,2688,2693,2708]},"signals":{"distressed_vacancy":0.0277,"absentee":0.1926,"free_clear":0.4132,"long_tenure":0.4763,"seasonal":0.1345,"older_stock":0.2846,"senior_owners":0.4327,"cost_burdened":0.2944,"small_multifamily":0.054},"signal_pct":{"distressed_vacancy":90.5,"absentee":14.3,"free_clear":95.2,"long_tenure":9.5,"seasonal":95.2,"older_stock":4.8,"senior_owners":95.2,"cost_burdened":66.7,"small_multifamily":14.3},"signal_n":{"distressed_vacancy":8195,"absentee":46969,"free_clear":81347,"long_tenure":93769,"seasonal":39863,"older_stock":84355,"senior_owners":85187,"cost_burdened":57959,"small_multifamily":16017}},"34039":{"name":"Union","scores":{"overall":40.4,"investment":26.6,"hotness":71.2,"affordability":27.7},"rank":{"investment":21,"hotness":3,"affordability":15,"overall":15},"coverage":{"investment":1.0,"hotness":1.0,"affordability":1.0},"stats":{"zhvi":642742,"appreciation_1yr":0.015,"appreciation_5yr":0.0543,"zori":2511,"rent_yield":0.0469,"days_to_pending":15.3,"sale_to_list":1.0439,"price_cut_share":0.1214,"inventory_yoy":0.0871,"income":103202,"value_to_income":6.23,"buy_to_rent":1.3},"trends":{"zhvi":{"m1":-0.0024,"m3":-0.0017,"m12":0.015},"zori":{"m1":0.0018,"m3":0.0031,"m12":0.0203},"days_to_pending":{"m1":-1.3333,"m3":-9.3333,"m12":1.0},"price_cut_share":{"m1":0.0061,"m3":0.0069,"m12":0.0028},"inventory":{"m1":0.1114,"m3":0.3382,"m12":0.0871}},"history":{"zhvi":[609232,612216,615822,619390,622219,622496,622783,624336,627990,632133,633686,633879,632742,632308,632566,633753,635957,638865,641428,644166,645868,644732,642322,641174],"zori":[2391,2409,2417,2420,2413,2407,2422,2435,2454,2462,2458,2463,2465,2466,2470,2477,2490,2503,2505,2503,2501,2503,2515,2515]},"signals":{"distressed_vacancy":0.0173,"absentee":0.4264,"free_clear":0.326,"long_tenure":0.541,"seasonal":0.0016,"older_stock":0.7035,"senior_owners":0.2916,"cost_burdened":0.3076,"small_multifamily":0.2479},"signal_pct":{"distressed_vacancy":52.4,"absentee":85.7,"free_clear":19.0,"long_tenure":61.9,"seasonal":9.5,"older_stock":100.0,"senior_owners":19.0,"cost_burdened":85.7,"small_multifamily":85.7},"signal_n":{"distressed_vacancy":3670,"absentee":86672,"free_clear":38019,"long_tenure":63082,"seasonal":339,"older_stock":149415,"senior_owners":34006,"cost_burdened":35862,"small_multifamily":52646}},"34007":{"name":"Camden","scores":{"overall":70.3,"investment":79.1,"hotness":51.9,"affordability":77.3},"rank":{"investment":2,"hotness":11,"affordability":4,"overall":2},"coverage":{"investment":1.0,"hotness":1.0,"affordability":1.0},"stats":{"zhvi":360180,"appreciation_1yr":0.0449,"appreciation_5yr":0.0832,"zori":1979,"rent_yield":0.0659,"days_to_pending":14.0,"sale_to_list":1.0063,"price_cut_share":0.1705,"inventory_yoy":0.0895,"income":88755,"value_to_income":4.06,"buy_to_rent":0.92},"trends":{"zhvi":{"m1":0.0017,"m3":0.0089,"m12":0.0449},"zori":{"m1":0.0036,"m3":0.0082,"m12":0.029},"days_to_pending":{"m1":-1.6667,"m3":-5.6667,"m12":2.0},"price_cut_share":{"m1":0.0033,"m3":-0.0141,"m12":0.006},"inventory":{"m1":0.0727,"m3":0.1791,"m12":0.0895}},"history":{"zhvi":[331128,332557,334774,336838,338129,338954,339596,340743,341961,343388,344803,345890,346695,347137,348139,349809,351871,353819,355360,356975,358632,359752,360290,360499],"zori":[1880,1882,1893,1894,1892,1893,1918,1929,1932,1920,1925,1926,1936,1944,1945,1949,1956,1966,1962,1964,1964,1976,1977,1986]},"signals":{"distressed_vacancy":0.0292,"absentee":0.3531,"free_clear":0.3488,"long_tenure":0.5622,"seasonal":0.0025,"older_stock":0.5548,"senior_owners":0.3075,"cost_burdened":0.2624,"small_multifamily":0.0794},"signal_pct":{"distressed_vacancy":95.2,"absentee":71.4,"free_clear":47.6,"long_tenure":90.5,"seasonal":38.1,"older_stock":76.2,"senior_owners":38.1,"cost_burdened":42.9,"small_multifamily":52.4},"signal_n":{"distressed_vacancy":6250,"absentee":71508,"free_clear":45705,"long_tenure":73663,"seasonal":543,"older_stock":118611,"senior_owners":40290,"cost_burdened":34386,"small_multifamily":16979}},"34031":{"name":"Passaic","scores":{"overall":35.2,"investment":41.7,"hotness":48.7,"affordability":17.0},"rank":{"investment":13,"hotness":12,"affordability":18,"overall":19},"coverage":{"investment":1.0,"hotness":1.0,"affordability":1.0},"stats":{"zhvi":603449,"appreciation_1yr":0.0436,"appreciation_5yr":0.0647,"zori":2304,"rent_yield":0.0458,"days_to_pending":18.3,"sale_to_list":1.0352,"price_cut_share":0.1289,"inventory_yoy":0.1736,"income":87522,"value_to_income":6.89,"buy_to_rent":1.33},"trends":{"zhvi":{"m1":0.0017,"m3":0.0104,"m12":0.0436},"zori":{"m1":-0.0015,"m3":0.0006,"m12":0.0201},"days_to_pending":{"m1":-1.3333,"m3":-8.0,"m12":2.0},"price_cut_share":{"m1":0.0117,"m3":0.0272,"m12":0.0172},"inventory":{"m1":0.1472,"m3":0.3175,"m12":0.1736}},"history":{"zhvi":[554784,558261,562497,566281,569290,570880,572890,574968,577084,578160,578202,578278,579006,580715,582915,585395,587615,590429,593474,597240,600939,602691,603572,604083],"zori":[2221,2227,2232,2220,2223,2222,2234,2233,2235,2244,2263,2268,2264,2271,2274,2287,2290,2300,2295,2303,2309,2311,2301,2298]},"signals":{"distressed_vacancy":0.0176,"absentee":0.4693,"free_clear":0.3462,"long_tenure":0.5609,"seasonal":0.0036,"older_stock":0.6923,"senior_owners":0.3205,"cost_burdened":0.3549,"small_multifamily":0.3074},"signal_pct":{"distressed_vacancy":57.1,"absentee":90.5,"free_clear":42.9,"long_tenure":85.7,"seasonal":47.6,"older_stock":95.2,"senior_owners":66.7,"cost_burdened":100.0,"small_multifamily":95.2},"signal_n":{"distressed_vacancy":3267,"absentee":83966,"free_clear":32876,"long_tenure":53270,"seasonal":668,"older_stock":128646,"senior_owners":30437,"cost_burdened":33701,"small_multifamily":57115}},"34027":{"name":"Morris","scores":{"overall":49.6,"investment":39.3,"hotness":72.4,"affordability":40.5},"rank":{"investment":14,"hotness":2,"affordability":13,"overall":10},"coverage":{"investment":1.0,"hotness":1.0,"affordability":1.0},"stats":{"zhvi":715574,"appreciation_1yr":0.0347,"appreciation_5yr":0.0604,"zori":2871,"rent_yield":0.0481,"days_to_pending":13.7,"sale_to_list":1.0443,"price_cut_share":0.1197,"inventory_yoy":0.1388,"income":137326,"value_to_income":5.21,"buy_to_rent":1.27},"trends":{"zhvi":{"m1":0.0029,"m3":0.0105,"m12":0.0347},"zori":{"m1":0.0013,"m3":0.0002,"m12":0.0094},"days_to_pending":{"m1":-1.0,"m3":-7.0,"m12":0.3333},"price_cut_share":{"m1":0.0161,"m3":0.0209,"m12":0.0129},"inventory":{"m1":0.1938,"m3":0.5581,"m12":0.1388}},"history":{"zhvi":[668737,671823,675494,678915,681766,683360,684857,686324,687864,689772,691855,693085,693761,693588,694557,696542,699309,702425,705213,708047,711235,713578,715753,717390],"zori":[2776,2769,2755,2768,2796,2792,2802,2808,2833,2845,2846,2840,2840,2853,2872,2874,2865,2874,2873,2874,2863,2864,2873,2874]},"signals":{"distressed_vacancy":0.0082,"absentee":0.2571,"free_clear":0.3551,"long_tenure":0.5408,"seasonal":0.0066,"older_stock":0.4891,"senior_owners":0.3031,"cost_burdened":0.2536,"small_multifamily":0.0684},"signal_pct":{"distressed_vacancy":4.8,"absentee":47.6,"free_clear":52.4,"long_tenure":57.1,"seasonal":71.4,"older_stock":57.1,"senior_owners":33.3,"cost_burdened":28.6,"small_multifamily":33.3},"signal_n":{"distressed_vacancy":1631,"absentee":49683,"free_clear":50980,"long_tenure":77644,"seasonal":1323,"older_stock":97585,"senior_owners":43512,"cost_burdened":36413,"small_multifamily":13646}},"34005":{"name":"Burlington","scores":{"overall":54.8,"investment":50.7,"hotness":34.9,"affordability":75.9},"rank":{"investment":10,"hotness":15,"affordability":6,"overall":6},"coverage":{"investment":1.0,"hotness":1.0,"affordability":1.0},"stats":{"zhvi":428058,"appreciation_1yr":0.0243,"appreciation_5yr":0.0726,"zori":2253,"rent_yield":0.0632,"days_to_pending":15.0,"sale_to_list":1.0009,"price_cut_share":0.1915,"inventory_yoy":0.1731,"income":108111,"value_to_income":3.96,"buy_to_rent":0.97},"trends":{"zhvi":{"m1":0.0016,"m3":0.0061,"m12":0.0243},"zori":{"m1":0.0037,"m3":0.0104,"m12":0.0265},"days_to_pending":{"m1":-1.6667,"m3":-8.6667,"m12":2.3333},"price_cut_share":{"m1":0.0088,"m3":0.0179,"m12":0.0054},"inventory":{"m1":0.1008,"m3":0.2638,"m12":0.1731}},"history":{"zhvi":[406802,409078,411288,412656,412954,413179,413431,414147,415000,416552,418034,419079,419514,419667,420050,420853,421845,423155,424349,425478,426555,427444,428127,428603],"zori":[2139,2151,2152,2159,2160,2182,2195,2198,2188,2193,2195,2196,2203,2203,2213,2216,2230,2228,2225,2227,2236,2244,2253,2262]},"signals":{"distressed_vacancy":0.0242,"absentee":0.2387,"free_clear":0.34,"long_tenure":0.5335,"seasonal":0.0028,"older_stock":0.3793,"senior_owners":0.3241,"cost_burdened":0.245,"small_multifamily":0.0532},"signal_pct":{"distressed_vacancy":71.4,"absentee":28.6,"free_clear":28.6,"long_tenure":38.1,"seasonal":42.9,"older_stock":28.6,"senior_owners":71.4,"cost_burdened":9.5,"small_multifamily":9.5},"signal_n":{"distressed_vacancy":4500,"absentee":42298,"free_clear":45876,"long_tenure":71979,"seasonal":513,"older_stock":70675,"senior_owners":43733,"cost_burdened":33057,"small_multifamily":9908}},"34021":{"name":"Mercer","scores":{"overall":57.7,"investment":50.8,"hotness":48.0,"affordability":72.9},"rank":{"investment":9,"hotness":13,"affordability":7,"overall":5},"coverage":{"investment":1.0,"hotness":1.0,"affordability":1.0},"stats":{"zhvi":453392,"appreciation_1yr":-0.0006,"appreciation_5yr":0.0693,"zori":2611,"rent_yield":0.0691,"days_to_pending":14.7,"sale_to_list":1.0028,"price_cut_share":0.1741,"inventory_yoy":0.0881,"income":100645,"value_to_income":4.5,"buy_to_rent":0.88},"trends":{"zhvi":{"m1":-0.0002,"m3":0.0014,"m12":-0.0006},"zori":{"m1":0.0034,"m3":0.0059,"m12":0.0146},"days_to_pending":{"m1":-2.3333,"m3":-12.3333,"m12":1.3333},"price_cut_share":{"m1":0.0111,"m3":0.0217,"m12":0.009},"inventory":{"m1":0.1077,"m3":0.2539,"m12":0.0881}},"history":{"zhvi":[438961,441717,444434,446627,447769,448803,449568,450826,452062,453161,453905,453906,453514,452958,452395,452203,451521,451550,451836,452780,453605,453555,453305,453317],"zori":[2498,2502,2510,2528,2526,2542,2549,2582,2582,2585,2572,2563,2567,2579,2589,2583,2591,2592,2602,2590,2595,2601,2611,2622]},"signals":{"distressed_vacancy":0.0255,"absentee":0.3785,"free_clear":0.377,"long_tenure":0.5574,"seasonal":0.0068,"older_stock":0.5134,"senior_owners":0.3141,"cost_burdened":0.2529,"small_multifamily":0.0861},"signal_pct":{"distressed_vacancy":76.2,"absentee":81.0,"free_clear":71.4,"long_tenure":81.0,"seasonal":76.2,"older_stock":66.7,"senior_owners":47.6,"cost_burdened":23.8,"small_multifamily":57.1},"signal_n":{"distressed_vacancy":3852,"absentee":54545,"free_clear":33768,"long_tenure":49927,"seasonal":1032,"older_stock":77590,"senior_owners":28133,"cost_burdened":22655,"small_multifamily":13007}},"34035":{"name":"Somerset","scores":{"overall":46.9,"investment":36.3,"hotness":62.6,"affordability":44.1},"rank":{"investment":16,"hotness":5,"affordability":11,"overall":13},"coverage":{"investment":1.0,"hotness":1.0,"affordability":1.0},"stats":{"zhvi":673150,"appreciation_1yr":0.0169,"appreciation_5yr":0.0611,"zori":2685,"rent_yield":0.0479,"days_to_pending":15.7,"sale_to_list":1.0218,"price_cut_share":0.1316,"inventory_yoy":0.0582,"income":140374,"value_to_income":4.8,"buy_to_rent":1.27},"trends":{"zhvi":{"m1":0.0007,"m3":0.0053,"m12":0.0169},"zori":{"m1":0.0012,"m3":0.0045,"m12":0.0323},"days_to_pending":{"m1":-3.3333,"m3":-14.3333,"m12":1.0},"price_cut_share":{"m1":0.0079,"m3":0.0106,"m12":0.0284},"inventory":{"m1":0.1905,"m3":0.4387,"m12":0.0582}},"history":{"zhvi":[641640,645599,649471,652905,655342,656598,657661,659221,660771,662124,662220,661479,660242,659054,659048,660865,663539,666139,667616,669421,671765,673025,673333,673091],"zori":[2558,2566,2557,2557,2555,2587,2583,2596,2591,2592,2602,2610,2621,2623,2642,2653,2675,2663,2674,2667,2679,2684,2684,2688]},"signals":{"distressed_vacancy":0.0096,"absentee":0.257,"free_clear":0.3589,"long_tenure":0.515,"seasonal":0.0016,"older_stock":0.3706,"senior_owners":0.2871,"cost_burdened":0.2304,"small_multifamily":0.0976},"signal_pct":{"distressed_vacancy":14.3,"absentee":42.9,"free_clear":57.1,"long_tenure":19.0,"seasonal":4.8,"older_stock":23.8,"senior_owners":9.5,"cost_burdened":4.8,"small_multifamily":66.7},"signal_n":{"distressed_vacancy":1284,"absentee":33615,"free_clear":34881,"long_tenure":50054,"seasonal":208,"older_stock":49529,"senior_owners":27905,"cost_burdened":22396,"small_multifamily":13049}},"34015":{"name":"Gloucester","scores":{"overall":78.3,"investment":81.6,"hotness":59.8,"affordability":90.8},"rank":{"investment":1,"hotness":6,"affordability":1,"overall":1},"coverage":{"investment":1.0,"hotness":1.0,"affordability":1.0},"stats":{"zhvi":389393,"appreciation_1yr":0.0392,"appreciation_5yr":0.0766,"zori":2160,"rent_yield":0.0666,"days_to_pending":13.0,"sale_to_list":1.0054,"price_cut_share":0.1937,"inventory_yoy":0.0048,"income":105115,"value_to_income":3.7,"buy_to_rent":0.92},"trends":{"zhvi":{"m1":0.002,"m3":0.0091,"m12":0.0392},"zori":{"m1":0.0044,"m3":0.0119,"m12":0.0395},"days_to_pending":{"m1":-2.3333,"m3":-11.0,"m12":0.0},"price_cut_share":{"m1":0.016,"m3":0.02,"m12":0.0235},"inventory":{"m1":0.1094,"m3":0.2061,"m12":0.0048}},"history":{"zhvi":[362118,363164,364577,366033,367193,368360,369556,371065,372333,373781,374780,375540,375836,376196,376997,378319,380034,382246,384167,385969,387565,388767,389515,389898],"zori":[2001,1992,2002,2021,2045,2060,2063,2065,2066,2078,2079,2077,2078,2093,2110,2117,2115,2114,2125,2134,2145,2147,2160,2173]},"signals":{"distressed_vacancy":0.0258,"absentee":0.1988,"free_clear":0.3212,"long_tenure":0.5347,"seasonal":0.0016,"older_stock":0.3519,"senior_owners":0.2977,"cost_burdened":0.2461,"small_multifamily":0.0567},"signal_pct":{"distressed_vacancy":81.0,"absentee":23.8,"free_clear":14.3,"long_tenure":42.9,"seasonal":19.0,"older_stock":14.3,"senior_owners":23.8,"cost_burdened":14.3,"small_multifamily":23.8},"signal_n":{"distressed_vacancy":3047,"absentee":22370,"free_clear":28961,"long_tenure":48220,"seasonal":194,"older_stock":41499,"senior_owners":26843,"cost_burdened":22189,"small_multifamily":6682}},"34001":{"name":"Atlantic","scores":{"overall":54.0,"investment":75.1,"hotness":24.5,"affordability":58.0},"rank":{"investment":4,"hotness":20,"affordability":9,"overall":7},"coverage":{"investment":1.0,"hotness":1.0,"affordability":1.0},"stats":{"zhvi":387406,"appreciation_1yr":0.0386,"appreciation_5yr":0.086,"zori":2077,"rent_yield":0.0643,"days_to_pending":27.7,"sale_to_list":0.9718,"price_cut_share":0.1942,"inventory_yoy":0.0508,"income":78050,"value_to_income":4.96,"buy_to_rent":0.95},"trends":{"zhvi":{"m1":0.0024,"m3":0.0119,"m12":0.0386},"zori":{"m1":0.0014,"m3":0.0114,"m12":0.0441},"days_to_pending":{"m1":-4.3333,"m3":-13.6667,"m12":2.0},"price_cut_share":{"m1":0.015,"m3":0.0396,"m12":-0.0121},"inventory":{"m1":0.0539,"m3":0.1382,"m12":0.0508}},"history":{"zhvi":[357826,359670,361546,363735,365247,366513,367584,369123,370464,371835,373007,374134,374901,375099,375322,376212,377511,379215,380660,382741,385141,386754,387581,387883],"zori":[1895,1882,1915,1910,1917,1935,1961,1977,1962,1985,1986,1997,2009,2032,2032,2042,2042,2036,2035,2050,2076,2071,2076,2085]},"signals":{"distressed_vacancy":0.0238,"absentee":0.3129,"free_clear":0.4002,"long_tenure":0.5394,"seasonal":0.1275,"older_stock":0.4059,"senior_owners":0.3649,"cost_burdened":0.298,"small_multifamily":0.0944},"signal_pct":{"distressed_vacancy":66.7,"absentee":57.1,"free_clear":81.0,"long_tenure":47.6,"seasonal":90.5,"older_stock":33.3,"senior_owners":90.5,"cost_burdened":71.4,"small_multifamily":61.9},"signal_n":{"distressed_vacancy":3149,"absentee":34276,"free_clear":30124,"long_tenure":40610,"seasonal":16856,"older_stock":53654,"senior_owners":27467,"cost_burdened":22437,"small_multifamily":12474}},"34011":{"name":"Cumberland","scores":{"overall":60.7,"investment":65.7,"hotness":31.4,"affordability":80.8},"rank":{"investment":6,"hotness":18,"affordability":3,"overall":4},"coverage":{"investment":1.0,"hotness":1.0,"affordability":1.0},"stats":{"zhvi":279804,"appreciation_1yr":0.0145,"appreciation_5yr":0.0721,"zori":1669,"rent_yield":0.0716,"days_to_pending":26.3,"sale_to_list":0.9866,"price_cut_share":0.2105,"inventory_yoy":-0.0126,"income":67436,"value_to_income":4.15,"buy_to_rent":0.85},"trends":{"zhvi":{"m1":0.0015,"m3":0.0053,"m12":0.0145},"zori":{"m1":-0.0005,"m3":0.0076,"m12":0.0304},"days_to_pending":{"m1":-3.0,"m3":-7.0,"m12":-1.0},"price_cut_share":{"m1":0.0068,"m3":0.0218,"m12":-0.0115},"inventory":{"m1":0.0489,"m3":0.1218,"m12":-0.0126}},"history":{"zhvi":[267465,269026,270337,271405,272508,273366,273651,273988,274265,275176,275860,276418,276606,276971,277542,277768,277800,277909,277931,278332,278732,279517,279923,279971],"zori":[1546,1554,1553,1554,1568,1572,1576,1579,1591,1603,1630,1625,1614,1607,1609,1618,1615,1625,1635,1661,1672,1675,1661,1670]},"signals":{"distressed_vacancy":0.0237,"absentee":0.3347,"free_clear":0.411,"long_tenure":0.5536,"seasonal":0.0065,"older_stock":0.513,"senior_owners":0.3204,"cost_burdened":0.2997,"small_multifamily":0.0762},"signal_pct":{"distressed_vacancy":61.9,"absentee":61.9,"free_clear":90.5,"long_tenure":76.2,"seasonal":66.7,"older_stock":61.9,"senior_owners":61.9,"cost_burdened":76.2,"small_multifamily":42.9},"signal_n":{"distressed_vacancy":1359,"absentee":17999,"free_clear":14705,"long_tenure":19808,"seasonal":370,"older_stock":29385,"senior_owners":11464,"cost_burdened":10725,"small_multifamily":4363}},"34037":{"name":"Sussex","scores":{"overall":65.1,"investment":58.1,"hotness":59.6,"affordability":76.7},"rank":{"investment":8,"hotness":7,"affordability":5,"overall":3},"coverage":{"investment":1.0,"hotness":1.0,"affordability":1.0},"stats":{"zhvi":451083,"appreciation_1yr":0.0316,"appreciation_5yr":0.0654,"zori":2210,"rent_yield":0.0588,"days_to_pending":17.0,"sale_to_list":1.0187,"price_cut_share":0.1424,"inventory_yoy":0.0505,"income":116186,"value_to_income":3.88,"buy_to_rent":1.04},"trends":{"zhvi":{"m1":0.0021,"m3":0.0069,"m12":0.0316},"zori":{"m1":0.0081,"m3":0.021,"m12":0.0394},"days_to_pending":{"m1":-3.3333,"m3":-14.6667,"m12":0.6667},"price_cut_share":{"m1":0.0149,"m3":0.0236,"m12":0.0085},"inventory":{"m1":0.1124,"m3":0.1952,"m12":0.0505}},"history":{"zhvi":[425172,427629,429504,430630,431184,431918,432412,433331,434239,435940,437343,438534,439702,440925,442255,443550,444871,446180,446955,447940,449078,450269,451107,451872],"zori":[2039,2067,2084,2101,2116,2114,2137,2130,2119,2102,2127,2149,2161,2169,2160,2160,2151,2167,2155,2170,2169,2201,2206,2223]},"signals":{"distressed_vacancy":0.017,"absentee":0.1627,"free_clear":0.3164,"long_tenure":0.5313,"seasonal":0.0443,"older_stock":0.4414,"senior_owners":0.2901,"cost_burdened":0.2614,"small_multifamily":0.0546},"signal_pct":{"distressed_vacancy":42.9,"absentee":9.5,"free_clear":4.8,"long_tenure":33.3,"seasonal":85.7,"older_stock":42.9,"senior_owners":14.3,"cost_burdened":38.1,"small_multifamily":19.0},"signal_n":{"distressed_vacancy":1068,"absentee":9401,"free_clear":15304,"long_tenure":25698,"seasonal":2783,"older_stock":27751,"senior_owners":14029,"cost_burdened":12641,"small_multifamily":3432}},"34019":{"name":"Hunterdon","scores":{"overall":48.2,"investment":32.0,"hotness":56.7,"affordability":57.1},"rank":{"investment":20,"hotness":8,"affordability":10,"overall":12},"coverage":{"investment":0.7,"hotness":1.0,"affordability":0.6},"stats":{"zhvi":643803,"appreciation_1yr":0.0271,"appreciation_5yr":0.0554,"zori":null,"rent_yield":null,"days_to_pending":16.0,"sale_to_list":1.0116,"price_cut_share":0.1249,"inventory_yoy":0.0896,"income":141715,"value_to_income":4.54,"buy_to_rent":null},"trends":{"zhvi":{"m1":0.0021,"m3":0.0101,"m12":0.0271},"days_to_pending":{"m1":-3.3333,"m3":-16.3333,"m12":1.0},"price_cut_share":{"m1":0.0112,"m3":0.021,"m12":-0.0116},"inventory":{"m1":0.1762,"m3":0.3916,"m12":0.0896}},"history":{"zhvi":[610881,612774,614960,617291,619029,619852,620243,621765,623873,626324,627230,626809,626102,625725,626388,628031,630417,632978,634863,636980,640302,642762,644250,644396]},"signals":{"distressed_vacancy":0.0111,"absentee":0.1486,"free_clear":0.3408,"long_tenure":0.5395,"seasonal":0.0045,"older_stock":0.3705,"senior_owners":0.3198,"cost_burdened":0.2507,"small_multifamily":0.0531},"signal_pct":{"distressed_vacancy":19.0,"absentee":4.8,"free_clear":33.3,"long_tenure":52.4,"seasonal":52.4,"older_stock":19.0,"senior_owners":57.1,"cost_burdened":19.0,"small_multifamily":4.8},"signal_n":{"distressed_vacancy":580,"absentee":7558,"free_clear":14757,"long_tenure":23362,"seasonal":236,"older_stock":19309,"senior_owners":13850,"cost_burdened":10856,"small_multifamily":2767}},"34041":{"name":"Warren","scores":{"overall":53.2,"investment":44.5,"hotness":54.2,"affordability":61.1},"rank":{"investment":11,"hotness":9,"affordability":8,"overall":8},"coverage":{"investment":1.0,"hotness":1.0,"affordability":1.0},"stats":{"zhvi":429548,"appreciation_1yr":0.0192,"appreciation_5yr":0.0573,"zori":2035,"rent_yield":0.0569,"days_to_pending":17.0,"sale_to_list":1.013,"price_cut_share":0.1623,"inventory_yoy":0.0424,"income":100869,"value_to_income":4.26,"buy_to_rent":1.07},"trends":{"zhvi":{"m1":0.0005,"m3":0.0045,"m12":0.0192},"zori":{"m1":0.0051,"m3":0.0139,"m12":0.0426},"days_to_pending":{"m1":-1.6667,"m3":-8.0,"m12":-0.6667},"price_cut_share":{"m1":0.0056,"m3":0.0304,"m12":0.0169},"inventory":{"m1":0.1027,"m3":0.2055,"m12":0.0424}},"history":{"zhvi":[408349,410587,412692,414093,415253,416452,417290,418475,419668,420967,421654,421712,421816,422159,423031,424005,424624,425536,426450,427595,428866,429483,429678,429484],"zori":[1842,1859,1875,1895,1893,1912,1921,1922,1936,1943,1960,1954,1961,1960,1963,1971,2000,1999,2002,2004,2015,2028,2031,2046]},"signals":{"distressed_vacancy":0.0169,"absentee":0.2494,"free_clear":0.3386,"long_tenure":0.5456,"seasonal":0.0024,"older_stock":0.469,"senior_owners":0.3163,"cost_burdened":0.2587,"small_multifamily":0.0784},"signal_pct":{"distressed_vacancy":38.1,"absentee":38.1,"free_clear":23.8,"long_tenure":66.7,"seasonal":33.3,"older_stock":52.4,"senior_owners":52.4,"cost_burdened":33.3,"small_multifamily":47.6},"signal_n":{"distressed_vacancy":791,"absentee":11319,"free_clear":11538,"long_tenure":18590,"seasonal":112,"older_stock":21942,"senior_owners":10777,"cost_burdened":8813,"small_multifamily":3666}},"34009":{"name":"Cape May","scores":{"overall":32.7,"investment":66.8,"hotness":31.0,"affordability":0.0},"rank":{"investment":5,"hotness":19,"affordability":21,"overall":21},"coverage":{"investment":1.0,"hotness":1.0,"affordability":1.0},"stats":{"zhvi":800123,"appreciation_1yr":0.0712,"appreciation_5yr":0.0765,"zori":2162,"rent_yield":0.0324,"days_to_pending":29.3,"sale_to_list":0.9779,"price_cut_share":0.2021,"inventory_yoy":-0.0528,"income":91128,"value_to_income":8.78,"buy_to_rent":1.88},"trends":{"zhvi":{"m1":0.006,"m3":0.0213,"m12":0.0712},"zori":{"m1":-0.0089,"m3":-0.0125,"m12":0.0632},"days_to_pending":{"m1":-3.6667,"m3":-13.6667,"m12":0.6667},"price_cut_share":{"m1":0.0267,"m3":0.0694,"m12":-0.0072},"inventory":{"m1":0.0533,"m3":0.1638,"m12":-0.0528}},"history":{"zhvi":[727343,730154,735131,739912,743330,744712,746625,749006,749953,748944,746605,745368,745931,748298,752356,757725,763709,770271,776621,783258,790377,795394,800339,804637],"zori":[null,null,null,null,null,null,2036,1947,1926,1986,2054,2061,2056,2086,2106,2108,2084,2071,2134,2196,2238,2163,2143,2179]},"signals":{"distressed_vacancy":0.0089,"absentee":0.1968,"free_clear":0.4106,"long_tenure":0.4802,"seasonal":0.4985,"older_stock":0.3474,"senior_owners":0.4404,"cost_burdened":0.2835,"small_multifamily":0.1025},"signal_pct":{"distressed_vacancy":9.5,"absentee":19.0,"free_clear":85.7,"long_tenure":14.3,"seasonal":100.0,"older_stock":9.5,"senior_owners":100.0,"cost_burdened":61.9,"small_multifamily":71.4},"signal_n":{"distressed_vacancy":885,"absentee":8831,"free_clear":14805,"long_tenure":17312,"seasonal":49655,"older_stock":34600,"senior_owners":15876,"cost_burdened":10220,"small_multifamily":10210}},"34033":{"name":"Salem","scores":{"overall":46.9,"investment":35.4,"hotness":9.4,"affordability":90.5},"rank":{"investment":17,"hotness":21,"affordability":2,"overall":14},"coverage":{"investment":0.7,"hotness":1.0,"affordability":0.6},"stats":{"zhvi":303162,"appreciation_1yr":0.0176,"appreciation_5yr":0.0685,"zori":null,"rent_yield":null,"days_to_pending":30.3,"sale_to_list":0.984,"price_cut_share":0.213,"inventory_yoy":0.1085,"income":79960,"value_to_income":3.79,"buy_to_rent":null},"trends":{"zhvi":{"m1":0.0035,"m3":0.0119,"m12":0.0176},"days_to_pending":{"m1":-5.3333,"m3":-13.3333,"m12":9.0},"price_cut_share":{"m1":0.0118,"m3":0.0144,"m12":-0.0169},"inventory":{"m1":0.0588,"m3":0.0893,"m12":0.1085}},"history":{"zhvi":[289717,291359,292687,293638,294095,294209,294311,294846,295673,296882,298041,298810,298561,297938,297097,296670,296752,297635,298416,299500,300885,302248,303217,304020]},"signals":{"distressed_vacancy":0.072,"absentee":0.2902,"free_clear":0.4328,"long_tenure":0.6189,"seasonal":0.0054,"older_stock":0.6019,"senior_owners":0.3593,"cost_burdened":0.2636,"small_multifamily":0.0757},"signal_pct":{"distressed_vacancy":100.0,"absentee":52.4,"free_clear":100.0,"long_tenure":100.0,"seasonal":57.1,"older_stock":81.0,"senior_owners":85.7,"cost_burdened":47.6,"small_multifamily":38.1},"signal_n":{"distressed_vacancy":1997,"absentee":7211,"free_clear":7632,"long_tenure":10914,"seasonal":150,"older_stock":16691,"senior_owners":6336,"cost_burdened":4648,"small_multifamily":2099}}}}